{
  "profile": {
    "name": "핫딜줍줍",
    "bio": "오늘의 핫딜 모음",
    "avatar": "images/profile.jpg"
  },
  "theme": {
    "accent": "#6B35C8"
  },
  "openChat": {
    "icon": "🔥",
    "title": "놓치면 품절! 실시간 알림 받기",
    "url": "https://open.kakao.com/o/pnOSHwBi"
  },
  "_banners_disabled": [
    {
      "title": "🎉 MEGA 뷰티쇼 진행중",
      "description": "뷰티 제품 1+1, ~50% 즉시할인 등",
      "url": "https://link.coupang.com/a/fpvrMQRkw8"
    }
  ],
  "malls": [
    {
      "id": "coupang",
      "name": "쿠팡",
      "disclosure": "• 이 포스팅은 쿠팡 파트너스 활동의 일환으로, 이에 따른 일정액의 수수료를 제공받습니다.\n• 와우회원 카드할인/쿠폰적용가 기준입니다.\n• 품절·가격 변동시 핫딜 종료! 실시간 알림 받고 놓치지 마세요!",
      "products": [
        {
          "name": "크리넥스 수프림 소프트 천연펄프 3겹 화장지 27m*30롤*1개",
          "price": "14,830원",
          "discount_rate": 29,
          "priceAt": "07.19 07:10",
          "image": "//thumbnail.coupangcdn.com/thumbnails/remote/492x492ex/image/retail/images/58433474886307-4c55277d-90c9-41a4-80d0-8ab14328b8d8.jpg",
          "url": "https://link.coupang.com/a/fuWNKWaxZk",
          "_ts": 1784412640.786272
        },
        {
          "name": "앨리쉬 자외선차단 양산 우산 초경량 암막",
          "price": "3,700원",
          "discount_rate": 81,
          "priceAt": "07.19 07:04",
          "image": "//thumbnail.coupangcdn.com/thumbnails/remote/492x492ex/image/vendor_inventory/5c05/a8999e47c6c030827c303b2cbe77784fc308b26c1bccc84e139186f69638.png",
          "url": "https://link.coupang.com/a/fuWkJifUhE",
          "_ts": 1784412248.0158231
        },
        {
          "name": "누아트 에어릿 88g 초경량 미니 휴대용 3in1 무선 손선풍기, 색상선택가능",
          "price": "2,900원",
          "discount_rate": 88,
          "priceAt": "07.18 23:10",
          "image": "//thumbnail.coupangcdn.com/thumbnails/remote/492x492ex/image/retail/images/49201307279165-57a1c49d-8869-486b-b9ec-a6d054d944b5.jpg",
          "url": "https://link.coupang.com/a/fuosQwhrbw",
          "_ts": 1784383819.984002
        },
        {
          "name": "프로그 일회용 수세미 엑스트라 스트롱 60개입*1개",
          "price": "2,340원",
          "discount_rate": 42,
          "priceAt": "07.18 17:32",
          "image": "//thumbnail.coupangcdn.com/thumbnails/remote/492x492ex/image/retail/images/430953114429949-6a4412b9-6f25-40e6-80d3-79765b1b4fae.jpg",
          "url": "https://link.coupang.com/a/ft0iPy4KWW",
          "_ts": 1784363527.9826581
        },
        {
          "name": "곰곰 촉촉 반숙란 (냉장) 30구*1개",
          "price": "11,400원",
          "discount_rate": 24,
          "priceAt": "07.18 13:45",
          "image": "//thumbnail.coupangcdn.com/thumbnails/remote/492x492ex/image/retail/images/1147310876361-66d4b381-bf7a-4d98-b28a-007daaf78c51.jpg",
          "url": "https://link.coupang.com/a/ftHprQWusu",
          "_ts": 1784349946.500572
        },
        {
          "name": "델몬트 베트남산 바나나, 800g 내외, 1개",
          "price": "2,200원",
          "discount_rate": 18,
          "priceAt": "07.18 12:23",
          "image": "//thumbnail.coupangcdn.com/thumbnails/remote/492x492ex/image/retail/images/141492625439443-a7bf5387-044b-4bb5-964d-a3d7d28de7bb.jpg",
          "url": "https://link.coupang.com/a/ftEeRRWdHM",
          "_ts": 1784345022.811616
        },
        {
          "name": "디유 울트라 텀블러 900ml*2세트",
          "price": "9,900원",
          "discount_rate": 45,
          "priceAt": "07.18 11:20",
          "image": "//thumbnail.coupangcdn.com/thumbnails/remote/492x492ex/image/retail/images/37072971791259-c4261024-7b9b-42b1-9dcd-70970c6a64c8.jpg",
          "url": "https://link.coupang.com/a/ftzLb38v3Q",
          "_ts": 1784341240.724583
        },
        {
          "name": "폰타나 발사믹 글레이즈, 250ml, 2개",
          "price": "10,870원",
          "discount_rate": 28,
          "priceAt": "07.18 10:42",
          "image": "//thumbnail.coupangcdn.com/thumbnails/remote/492x492ex/image/retail/images/890444865790989-120d22dd-ce96-4783-a3a0-f3a81f585d2b.jpg",
          "url": "https://link.coupang.com/a/ftwJuREGE8",
          "_ts": 1784338926.463089
        },
        {
          "name": "후아유 유니 카라 바시티 패딩 자켓 M95",
          "price": "17,520원",
          "discount_rate": 44,
          "priceAt": "07.18 09:47",
          "image": "//thumbnail.coupangcdn.com/thumbnails/remote/492x492ex/image/rs_quotation_api/85cdwqjb/4329a9e1652141a5a4eb0175596b1f63.jpg",
          "url": "https://link.coupang.com/a/ftsW9dLU9A",
          "_ts": 1784335651.007621
        },
        {
          "name": "한성기업 콤비부어스트 파티 후랑크 소시지, 330g, 3개",
          "price": "9,950원",
          "discount_rate": 29,
          "priceAt": "07.18 09:12",
          "image": "//thumbnail.coupangcdn.com/thumbnails/remote/492x492ex/image/retail/images/8a27c175-74e3-4ef4-a03f-d88988f95f276745479876273613876.png",
          "url": "https://link.coupang.com/a/ftqiJBb39w",
          "_ts": 1784333576.345342
        }
      ]
    },
    {
      "id": "toss",
      "name": "토스쇼핑",
      "disclosure": "• 이 포스팅은 토스쇼핑 쉐어링크 활동의 일환으로, 이에 따른 일정액의 수수료를 제공받습니다.\n• 품절·가격 변동시 핫딜 종료! 실시간 알림 받고 놓치지 마세요!",
      "products": [
        {
          "name": "전남 무안 양파, 중, 5kg, 1개",
          "price": "6,755원",
          "discount_rate": 75,
          "priceAt": "07.19 08:45",
          "image": "https://shopping.toss.im/live/temp/2025-04-22/a651c74c-be3b-406d-9c63-6b02d1c2cbe2.jpeg",
          "url": "https://toss.im/_m/b0hTpoEt",
          "_ts": 1784418339.4424808
        },
        {
          "name": "순수식품 300달톤 저분자 피쉬 콜라겐, 90정, 3박스",
          "price": "9,900원",
          "discount_rate": 78,
          "priceAt": "07.19 08:45",
          "image": "https://shopping.toss.im/live/temp/2026-07-03/739e0b9e-df5c-475e-8da3-8e340a3b938e.jpeg",
          "url": "https://toss.im/_m/50fEzOn2",
          "_ts": 1784418336.781205
        },
        {
          "name": "푸드앳홈 냉동 생선까스, 1kg, 1팩",
          "price": "7,500원",
          "discount_rate": 62,
          "priceAt": "07.19 08:45",
          "image": "https://shopping.toss.im/live/temp/2025-06-12/30d62d22-99a6-4b38-a9a0-76c0bf832dce.jpeg",
          "url": "https://toss.im/_m/hz9BPosd",
          "_ts": 1784418333.852303
        },
        {
          "name": "경추 안마기, 가성비 저주파 마사지기, 블루블랙, 1개",
          "price": "7,900원",
          "discount_rate": 47,
          "priceAt": "07.18 21:00",
          "image": "https://shopping.toss.im/live/temp/2026-05-29/1d3e6ea8-5942-4295-b3f4-20f8d2eb7ab3.jpeg",
          "url": "https://toss.im/_m/1xiJtTz4",
          "_ts": 1784376027.279624
        },
        {
          "name": "알로코리아 라이트 GaN 25W 초고속 멀티 충전기 어댑터 UC225GPD, 화이트, 1개",
          "price": "8,900원",
          "discount_rate": 55,
          "priceAt": "07.18 21:00",
          "image": "https://shopping.toss.im/live/temp/2025-12-08/89f32b36-fac1-4b61-b4ac-cf1c894cefa6.jpeg",
          "url": "https://toss.im/_m/ZFjnhZis",
          "_ts": 1784376024.5045938
        },
        {
          "name": "광천김 곱창김 도시락김, 5g, 27개, 1세트",
          "price": "9,900원",
          "discount_rate": 50,
          "priceAt": "07.18 18:20",
          "image": "https://shopping.toss.im/live/temp/2025-11-19/7b33a77a-96e1-4ed7-a640-4d26cef896dd.jpeg",
          "url": "https://toss.im/_m/roSpDwqi",
          "_ts": 1784366433.4190972
        },
        {
          "name": "허블리 여성 냉감 플리츠 와이드 팬츠, 옵션6, free, 1장",
          "price": "5,723원",
          "discount_rate": 64,
          "priceAt": "07.18 18:20",
          "image": "https://shopping.toss.im/live/temp/2026-05-26/f33dde15-d475-4436-a737-ea09652aecb8.jpeg",
          "url": "https://toss.im/_m/FZJ1eEVa",
          "_ts": 1784366430.04413
        },
        {
          "name": "올바른 슈퍼 프로바이오틱스 생유산균 19 비타민D, 30포, 2박스",
          "price": "5,100원",
          "discount_rate": 87,
          "priceAt": "07.18 15:00",
          "image": "https://shopping.toss.im/live/temp/2025-08-11/61535351-7e00-43fe-beda-ae65d776c7de.png",
          "url": "https://toss.im/_m/l2TTnNWo",
          "_ts": 1784354429.545198
        },
        {
          "name": "세제의기본 과탄산소다, 2kg, 1개",
          "price": "8,900원",
          "discount_rate": 57,
          "priceAt": "07.18 15:00",
          "image": "https://shopping.toss.im/live/temp/2025-06-29/ee9f4526-984e-421b-96f5-cdc9eb0a2a8d.jpeg",
          "url": "https://toss.im/_m/DKDtJB31",
          "_ts": 1784354426.752566
        },
        {
          "name": "잇담 햇 초록사과 썸머킹 아오리 사과, 꼬마(한입)소과, 2kg, 1개",
          "price": "8,900원",
          "discount_rate": 59,
          "priceAt": "07.18 15:00",
          "image": "https://shopping.toss.im/live/product/4624931/ce7a899a-7b7b-410a-8452-d52c92bb9b65.jpeg",
          "url": "https://toss.im/_m/f4CfU5BC",
          "_ts": 1784354423.964739
        },
        {
          "name": "스테이퍼퓸 밤쉘, 80ml, 1개",
          "price": "7,900원",
          "discount_rate": 75,
          "priceAt": "07.18 11:45",
          "image": "https://shopping.toss.im/live/temp/2025-10-21/2949603d-2b8a-44c9-a4d3-3ea6e24efd64.jpeg",
          "url": "https://toss.im/_m/HUEpWD9w",
          "_ts": 1784342726.700448
        },
        {
          "name": "위니즈 질레트 호환용 퓨전 프로쉴드 5중 면도날, 12개 + 면도기, 1개",
          "price": "9,506원",
          "discount_rate": 60,
          "priceAt": "07.18 11:45",
          "image": "https://shopping.toss.im/live/temp/2026-04-05/a58d1887-f8ec-41eb-9f33-6545a2ca7167.jpeg",
          "url": "https://toss.im/_m/dpC8eeWp",
          "_ts": 1784342724.118571
        },
        {
          "name": "광동 썬키스트 피스타치오 언스위트, 190ml, 24개",
          "price": "9,900원",
          "discount_rate": 64,
          "priceAt": "07.18 11:45",
          "image": "https://shopping.toss.im/live/temp/2026-07-14/0d13fed7-2412-4e44-9845-50e4fef41e0c.jpeg",
          "url": "https://toss.im/_m/5YlziOIk",
          "_ts": 1784342721.4255831
        },
        {
          "name": "이롬 황성주 박사의 국산콩 두유 무가당, 190ml, 16팩",
          "price": "4,900원",
          "discount_rate": 70,
          "image": "https://shopping.toss.im/live/temp/2026-04-17/073eaf80-05ff-4fc5-bd33-7eb7ac22363c.jpeg",
          "url": "https://toss.im/_m/vyi46s17",
          "_rank": 2,
          "_product_id": "1568528867",
          "_ts": 1784415712.6415098
        },
        {
          "name": "스파클 생수, 무라벨, 500ml, 80개",
          "price": "7,840원",
          "discount_rate": 67,
          "image": "https://shopping.toss.im/live/temp/2026-03-09/1ca62748-4d8c-4131-a992-6f968acf7829.jpeg",
          "url": "https://toss.im/_m/DiFTIObn",
          "_rank": 3,
          "_product_id": "10143179",
          "_ts": 1784415712.6415098
        },
        {
          "name": "퓨어스트 라이트 초순수 플레인 아기물티슈 캡형, 100매, 10팩",
          "price": "4,700원",
          "discount_rate": 60,
          "image": "https://shopping.toss.im/live/temp/2026-01-16/e7778601-d6a5-4390-ba58-4e286b0ced0e.jpeg",
          "url": "https://toss.im/_m/ZhKS6rh3",
          "_rank": 4,
          "_product_id": "651373711",
          "_ts": 1784415712.6415098
        },
        {
          "name": "에뛰드 베이킹 파우더 모공 클렌징폼, 160g, 1개",
          "price": "3,000원",
          "discount_rate": 62,
          "image": "https://shopping.toss.im/live/temp/2026-07-06/91887f97-f3d4-430e-9167-5043f9fca7c6.jpeg",
          "url": "https://toss.im/_m/lxGIOK8v",
          "_rank": 6,
          "_product_id": "2421955233",
          "_ts": 1784415712.6415098
        },
        {
          "name": "맘스럽 아토클래식 물티슈, 100매입, 20팩",
          "price": "7,990원",
          "discount_rate": 67,
          "image": "https://shopping.toss.im/live/temp/2026-07-01/cbcba31d-9c3d-4336-b01c-da1112ebe230.jpeg",
          "url": "https://toss.im/_m/JSoQFq7g",
          "_rank": 7,
          "_product_id": "2334877747",
          "_ts": 1784415712.6415098
        },
        {
          "name": "랜선식당 연탄불고기, 250g, 4개",
          "price": "8,300원",
          "discount_rate": 79,
          "image": "https://shopping.toss.im/live/temp/2026-07-02/f2753853-f811-4687-b2dc-774c7be576fc.jpeg",
          "url": "https://toss.im/_m/zaKyWLHn",
          "_rank": 8,
          "_product_id": "2278446229",
          "_ts": 1784415712.6415098
        },
        {
          "name": "순수식품 칼슘 마그네슘 비타민D 아연 망간, 90정, 1박스",
          "price": "3,900원",
          "discount_rate": 70,
          "image": "https://shopping.toss.im/live/temp/2026-06-30/2fa27ce7-49c0-4917-ac4f-fcde8870c713.jpeg",
          "url": "https://toss.im/_m/FQFr0pHj",
          "_rank": 9,
          "_product_id": "11681645",
          "_ts": 1784415712.6415098
        },
        {
          "name": "듀오덤 밴드, 혼합형, 8매입, 1개",
          "price": "3,800원",
          "discount_rate": 70,
          "image": "https://shopping.toss.im/live/temp/2025-05-26/61cf7eec-937b-400d-840f-e953c3e3bb10.jpeg",
          "url": "https://toss.im/_m/lSGsYvVz",
          "_rank": 10,
          "_product_id": "106565105",
          "_ts": 1784415712.6415098
        },
        {
          "name": "맘스럽 아토워시 프렌치 라벤더 캡슐세제 파우치형, 8g, 200개입",
          "price": "5,700원",
          "discount_rate": 71,
          "image": "https://shopping.toss.im/live/temp/2025-05-14/52c78bea-ea6e-40df-92a3-fca69d1d7141.jpeg",
          "url": "https://toss.im/_m/1JGAXtnt",
          "_rank": 11,
          "_product_id": "102193743",
          "_ts": 1784415712.6415098
        },
        {
          "name": "일양약품 눈건강 루테인 골드, 500mg, 30캡슐, 6박스",
          "price": "10,800원",
          "discount_rate": 96,
          "image": "https://shopping.toss.im/live/temp/2025-04-17/eb14e497-d99c-44b1-b6cf-828c7d796914.jpeg",
          "url": "https://toss.im/_m/pJg81Wmo",
          "_rank": 12,
          "_product_id": "7707001",
          "_ts": 1784415712.6415098
        },
        {
          "name": "일화 초정 탄산수 플레인, 250ml, 30개",
          "price": "6,900원",
          "discount_rate": 50,
          "image": "https://shopping.toss.im/live/temp/2025-07-30/cad91a6f-29f0-4798-8417-c55c7e069d75.jpeg",
          "url": "https://toss.im/_m/h1DEebS6",
          "_rank": 13,
          "_product_id": "48217065",
          "_ts": 1784415712.6415098
        },
        {
          "name": "성주 꿀참외, 랜덤과, 10kg, 1박스",
          "price": "6,300원",
          "discount_rate": 68,
          "image": "https://shopping.toss.im/live/temp/2026-07-16/61bedfb3-5dab-48db-b7b4-7446e23cd46f.jpeg",
          "url": "https://toss.im/_m/3hZwEQdh",
          "_rank": 14,
          "_product_id": "2494791539",
          "_ts": 1784415712.6415098
        },
        {
          "name": "터치 라이트 아토캡 고농축 캡슐세제, 8g, 120개입, 1개",
          "price": "4,500원",
          "discount_rate": 71,
          "image": "https://shopping.toss.im/live/temp/2026-06-24/34d2976a-b1b3-45aa-a4d1-0c5f0d7c1fc6.jpeg",
          "url": "https://toss.im/_m/PPxtyam7",
          "_rank": 15,
          "_product_id": "2316069149",
          "_ts": 1784415712.6415098
        },
        {
          "name": "유한메디카 징코 플러스엔탑 혈행 기억력 케어, 60정, 1개",
          "price": "4,500원",
          "discount_rate": 90,
          "image": "https://shopping.toss.im/live/temp/2026-07-01/d5028dc4-5249-47c9-96b2-23db09472f21.jpeg",
          "url": "https://toss.im/_m/xHzs7BRy",
          "_rank": 16,
          "_product_id": "37386349",
          "_ts": 1784415712.6415098
        },
        {
          "name": "정다운농장 국내산 백다다기 오이, 피클용, 4.5kg, 1박스",
          "price": "6,900원",
          "discount_rate": 59,
          "image": "https://shopping.toss.im/live/temp/2026-04-25/902d56d6-d862-4701-8d18-f8281815c193.jpeg",
          "url": "https://toss.im/_m/XIQOfW1A",
          "_rank": 17,
          "_product_id": "1692951403",
          "_ts": 1784415712.6415098
        },
        {
          "name": "연세유업 세브란스 A2 프로틴 초코맛, 190ml, 16개",
          "price": "14,900원",
          "discount_rate": 50,
          "image": "https://shopping.toss.im/live/temp/2026-05-10/e0700e5d-b1fa-48b0-be4c-900511b6b59d.jpeg",
          "url": "https://toss.im/_m/Nguky9k2",
          "_rank": 18,
          "_product_id": "1438581063",
          "_ts": 1784415712.6415098
        },
        {
          "name": "숨 데일리 화장지, 천연펄프, 3겹, 30m, 30롤, 1팩",
          "price": "9,900원",
          "discount_rate": 37,
          "image": "https://shopping.toss.im/live/temp/2025-12-29/df810c2d-0d4e-4005-bade-777c1547de3b.jpeg",
          "url": "https://toss.im/_m/f3IaOH2g",
          "_rank": 19,
          "_product_id": "503276161",
          "_ts": 1784415712.6415098
        },
        {
          "name": "후디스 무가당 플레인 그릭요거트, 400g, 2개",
          "price": "7,900원",
          "discount_rate": 38,
          "image": "https://shopping.toss.im/live/temp/2026-06-09/069859ea-3ad7-4e7f-9f77-92cd73538e14.jpeg",
          "url": "https://toss.im/_m/floKyted",
          "_rank": 20,
          "_product_id": "1960824601",
          "_ts": 1784415712.6415098
        },
        {
          "name": "고당도 경북 부사 못난이사과, 10kg, 1박스",
          "price": "14,900원",
          "discount_rate": 62,
          "image": "https://shopping.toss.im/live/temp/2026-05-17/5aa70609-2ac8-4b7b-88a7-e0e710e70b10.png",
          "url": "https://toss.im/_m/Jfx7Ykoh",
          "_rank": 21,
          "_product_id": "2400642485",
          "_ts": 1784415712.6415098
        },
        {
          "name": "프로프루 성주 꿀참외, 가정용, 5kg, 1박스",
          "price": "9,800원",
          "discount_rate": 80,
          "image": "https://shopping.toss.im/live/temp/2026-06-11/5fbd465a-2615-400a-8da7-6e46bfa944e1.jpeg",
          "url": "https://toss.im/_m/xZcbx8Oo",
          "_rank": 22,
          "_product_id": "2235106829",
          "_ts": 1784415712.6415098
        },
        {
          "name": "딱딱이 복숭아, 2kg, 1박스",
          "price": "11,500원",
          "discount_rate": 60,
          "image": "https://shopping.toss.im/live/temp/2026-07-13/4821d240-db66-4fb6-acc3-a67610cc61eb.png",
          "url": "https://toss.im/_m/pBnl4j3A",
          "_rank": 23,
          "_product_id": "2477147977",
          "_ts": 1784415712.6415098
        },
        {
          "name": "듀록 꽃삼겹살, 4mm, 500g, 4개",
          "price": "20,988원",
          "discount_rate": 44,
          "image": "https://shopping.toss.im/live/temp/2026-06-29/61e016a6-f105-4ae5-a904-a8cec4e56440.jpeg",
          "url": "https://toss.im/_m/tAuWBaj8",
          "_rank": 24,
          "_product_id": "2360360557",
          "_ts": 1784415712.6415098
        }
      ]
    },
    {
      "id": "coupang_more",
      "name": "더 많은 핫딜보기",
      "disclosure": "• 이 포스팅은 쿠팡 파트너스 활동의 일환으로, 이에 따른 일정액의 수수료를 제공받습니다.\n• 와우회원 카드할인/쿠폰적용가 기준입니다.\n• 품절·가격 변동시 핫딜 종료! 실시간 알림 받고 놓치지 마세요!",
      "products": [
        {
          "name": "누아트 날개없는 넥밴드 휴대용 선풍기",
          "price": "7,900원",
          "discount_rate": 33,
          "priceAt": "07.19 08:24",
          "image": "//thumbnail.coupangcdn.com/thumbnails/remote/492x492ex/image/retail/images/15924860402622-53067aa6-3334-42b5-84ee-0a405747a41d.jpg",
          "url": "https://link.coupang.com/a/fu168SEpZA",
          "_ts": 1784417095.544491
        },
        {
          "name": "센텔리안24 마데카 크림 미스트, 120ml, 2개",
          "price": "18,510원",
          "discount_rate": 29,
          "priceAt": "07.19 08:22",
          "image": "//thumbnail.coupangcdn.com/thumbnails/remote/492x492ex/image/vendor_inventory/image_audit/prod/15ab87f8-c241-4168-ba16-a1bf557c9b1b_fixing_v2.png",
          "url": "https://link.coupang.com/a/fu1XzHzJgz",
          "_ts": 1784416962.74966
        },
        {
          "name": "하림 안동식 찜닭 밀키트, 1.403kg, 1개",
          "price": "10,350원",
          "discount_rate": 20,
          "priceAt": "07.19 08:22",
          "image": "//thumbnail.coupangcdn.com/thumbnails/remote/492x492ex/image/retail/images/384153881633646-4ad7fdb6-1aba-43f6-974b-210131d48c1a.jpg",
          "url": "https://link.coupang.com/a/fu1WFybYLQ",
          "_ts": 1784416953.432252
        },
        {
          "name": "쿤달 스칼프 마사지 샴푸 브러쉬, 보라색, 1개",
          "price": "6,100원",
          "discount_rate": 32,
          "priceAt": "07.19 08:20",
          "image": "//thumbnail.coupangcdn.com/thumbnails/remote/492x492ex/image/vendor_inventory/image_audit/stage/manual/8774992804084805-06eed9d2-29ad-4d62-a09b-18b48bf341ee_1752743125813.PNG",
          "url": "https://link.coupang.com/a/fu1MY8vuCq",
          "_ts": 1784416820.727322
        },
        {
          "name": "그린비아 영양 케어 영양식 구수한맛, 200ml, 18개",
          "price": "16,200원",
          "discount_rate": 29,
          "priceAt": "07.19 08:18",
          "image": "//thumbnail.coupangcdn.com/thumbnails/remote/492x492ex/image/retail/images/2026/05/12/15/7/039af8bb-336b-4ec5-abed-b1baba66f95b.jpg",
          "url": "https://link.coupang.com/a/fu1DhsBitE",
          "_ts": 1784416689.484928
        },
        {
          "name": "DDJJ 3in1 자동 손톱깎이 충전식 전동 손톱깎이 손톱 정리 도구 네일 그라인더 led 조명, 그레이, ",
          "price": "15,350원",
          "discount_rate": 34,
          "priceAt": "07.19 07:59",
          "image": "//thumbnail.coupangcdn.com/thumbnails/remote/492x492ex/image/vendor_inventory/image_audit/stage/manual/cb76a4fd552ec73e4002725fe8e10b9288d12c857051ab3b26b8912707a1_1781589506256.jpg",
          "url": "https://link.coupang.com/a/fu0kkEfqx2",
          "_ts": 1784415595.092555
        },
        {
          "name": "스카치브라이트 제로 스크래치 도트 수세미 10개입",
          "price": "7,190원",
          "discount_rate": 35,
          "priceAt": "07.19 07:59",
          "image": "//thumbnail.coupangcdn.com/thumbnails/remote/492x492ex/image/retail/images/378388040087512-4768b756-ec77-4d9e-8dda-5e1e14fc2006.jpg",
          "url": "https://link.coupang.com/a/fu0jv8jKfI",
          "_ts": 1784415582.374905
        },
        {
          "name": "이자녹스 유브이 선프로 선크림 365 데일리 SPF50+ PA+++ 선블록/선크림/선로션, 70ml, 2개",
          "price": "20,100원",
          "discount_rate": 40,
          "priceAt": "07.19 07:57",
          "image": "//thumbnail.coupangcdn.com/thumbnails/remote/492x492ex/image/retail/images/2026/04/01/16/5/74ab69b6-1c37-4931-b932-ad15f50a9c12.png",
          "url": "https://link.coupang.com/a/fuZ9OnEMKq",
          "_ts": 1784415450.900332
        },
        {
          "name": "블랙야크 S-매쉬햇 모자 캡모자 낚시모자 땀방지 메쉬햇 블랙",
          "price": "17,440원",
          "discount_rate": 24,
          "priceAt": "07.19 07:41",
          "image": "//thumbnail.coupangcdn.com/thumbnails/remote/492x492ex/image/vendor_inventory/72d6/f6881134783caef8c34b8a45c7a49d97a8c202ccfe93d17204346fcc4720.jpg",
          "url": "https://link.coupang.com/a/fuYZZTJEES",
          "_ts": 1784414480.4118621
        },
        {
          "name": "콘티고 바이론 2.0 텀블러 470ml*1개",
          "price": "9,990원",
          "discount_rate": 55,
          "priceAt": "07.19 07:37",
          "image": "//thumbnail.coupangcdn.com/thumbnails/remote/492x492ex/image/retail/images/2025/08/05/13/6/8a95bc3b-fde2-4c30-976f-dfc03804bfef.jpg",
          "url": "https://link.coupang.com/a/fuYHum6kzA",
          "_ts": 1784414230.5315351
        },
        {
          "name": "알텐바흐 인덕션 헥사 통5중 프라이팬세트 2종, 프라이팬30cm+ 궁중팬30cm+ 유리커버30cm",
          "price": "78,900원",
          "discount_rate": 21,
          "priceAt": "07.19 07:24",
          "image": "//thumbnail.coupangcdn.com/thumbnails/remote/492x492ex/image/retail/images/103418620557218-242b0ed4-c483-4639-824c-035ecd26323d.png",
          "url": "https://link.coupang.com/a/fuXPemoFK8",
          "_ts": 1784413497.91377
        },
        {
          "name": "투데이넛 너트한줌 요거트 견과세트 600g 1세트",
          "price": "15,820원",
          "discount_rate": 12,
          "priceAt": "07.19 07:22",
          "image": "//thumbnail.coupangcdn.com/thumbnails/remote/492x492ex/image/retail/images/308513359822038-d05e9981-3c5a-45b3-bbd1-55eb16ef51e4.jpg",
          "url": "https://link.coupang.com/a/fuXFC9b5oW",
          "_ts": 1784413365.3964841
        },
        {
          "name": "우리차 콘푸레이크 천마차 18g*110개입*1개",
          "price": "11,600원",
          "discount_rate": 32,
          "priceAt": "07.19 07:08",
          "image": "//thumbnail.coupangcdn.com/thumbnails/remote/492x492ex/image/retail/images/86795193934867-6f4bfc2c-de28-4fb8-9e98-f45434c6bab7.jpg",
          "url": "https://link.coupang.com/a/fuWD7gGctE",
          "_ts": 1784412505.963996
        },
        {
          "name": "코카콜라 제로 무라벨, 370ml, 24개",
          "price": "16,980원",
          "discount_rate": 15,
          "priceAt": "07.19 07:04",
          "image": "//thumbnail.coupangcdn.com/thumbnails/remote/492x492ex/image/retail/images/357307576315419-db13617b-51b2-47fd-b370-1d6cc70dc5c2.jpg",
          "url": "https://link.coupang.com/a/fuWlfKujm0",
          "_ts": 1784412254.776663
        },
        {
          "name": "헤드앤숄더 2in1 쿨멘솔 샴푸 겸 컨디셔너 프루티향, 800ml, 1개",
          "price": "13,400원",
          "discount_rate": 29,
          "priceAt": "07.18 23:03",
          "image": "//thumbnail.coupangcdn.com/thumbnails/remote/492x492ex/image/retail/images/60602366159232-e55bcaf9-4166-4f95-a62d-f352fd12418e.jpg",
          "url": "https://link.coupang.com/a/fun1s8C3Km",
          "_ts": 1784383435.169535
        },
        {
          "name": "하이디라오 마라샹궈 소스, 220g, 1개",
          "price": "2,580원",
          "discount_rate": 25,
          "priceAt": "07.18 17:46",
          "image": "//thumbnail.coupangcdn.com/thumbnails/remote/492x492ex/image/vendor_inventory/bef1/982196f16d1564cb0878dff2126fba9a21bc81ff4f3528dd92d0a881fa42.jpg",
          "url": "https://link.coupang.com/a/ft1jRytlNA",
          "_ts": 1784364374.2025862
        },
        {
          "name": "AHC 마스터즈 멜라 프로텍트 워터풀 선크림 SPF50+ PA++++, 40ml, 2개",
          "price": "8,800원",
          "discount_rate": 36,
          "priceAt": "07.18 17:15",
          "image": "//thumbnail.coupangcdn.com/thumbnails/remote/492x492ex/image/retail/images/3eea47b7-28e9-4c25-9fb6-bb6bb16f4ded7406309591297614751.png",
          "url": "https://link.coupang.com/a/ftY80mSczk",
          "_ts": 1784362545.6999948
        },
        {
          "name": "코디 뉴플라워 천연펄프 미용티슈 2겹, 250매, 6개",
          "price": "7,190원",
          "discount_rate": 23,
          "priceAt": "07.18 15:53",
          "image": "//thumbnail.coupangcdn.com/thumbnails/remote/492x492ex/image/retail/images/456801513087351-aff9606f-9e64-429a-bde0-9fba88244385.jpg",
          "url": "https://link.coupang.com/a/ftTfhE7iG4",
          "_ts": 1784357593.758232
        },
        {
          "name": "블라우풍트 슬림 아이오닉 미니 뿌리 볼륨 고데기",
          "price": "19,930원",
          "discount_rate": 40,
          "priceAt": "07.18 15:12",
          "image": "//thumbnail.coupangcdn.com/thumbnails/remote/492x492ex/image/retail/images/40229990191585-9eb3e77b-082b-4ef5-b51a-e767285d3bac.jpg",
          "url": "https://link.coupang.com/a/ftQk7na7zw",
          "_ts": 1784355152.28976
        },
        {
          "name": "소미 시오다래, 320g, 1개",
          "price": "5,470원",
          "discount_rate": 22,
          "priceAt": "07.18 15:04",
          "image": "//thumbnail.coupangcdn.com/thumbnails/remote/492x492ex/image/retail/images/1769763913803137-e8b0d540-a76c-4965-8415-eaf23262cc4c.jpg",
          "url": "https://link.coupang.com/a/ftPKQskRUG",
          "_ts": 1784354660.497441
        },
        {
          "name": "이자녹스 테르비나 어드밴스드 리제너레이팅 2종 세트",
          "price": "58,680원",
          "discount_rate": 31,
          "priceAt": "07.18 11:22",
          "image": "//thumbnail.coupangcdn.com/thumbnails/remote/492x492ex/image/vendor_inventory/image_audit/prod/76dab027-0c41-40a3-b908-131981189382_fixing_v2.png",
          "url": "https://link.coupang.com/a/ftzUNksGQK",
          "_ts": 1784341367.0935419
        },
        {
          "name": "클라렌 화이트나우 치아 미백제 8p, 8g, 1개",
          "price": "5,850원",
          "discount_rate": 16,
          "priceAt": "07.18 10:36",
          "image": "//thumbnail.coupangcdn.com/thumbnails/remote/492x492ex/image/1025_amir_coupang_oct_80k/6998/02c61d50cda1fc35e266f692329e81b635b2d2bf4518468203a91eccc864.jpg",
          "url": "https://link.coupang.com/a/ftwzM3AOD6",
          "_ts": 1784338560.978233
        },
        {
          "name": "질레트 정품 퓨전 프로글라이드 센서티브 2 in 1 퓨어스포츠 쉐이빙 젤, 170g, 2개",
          "price": "7,900원",
          "discount_rate": 21,
          "priceAt": "07.18 10:11",
          "image": "https://thumbnail.coupangcdn.com/thumbnails/remote/657x657q90trim/image/retail/images/791219214434627-dc51c017-a1e6-4bf1-9ec8-806b5e6d98c8.jpg",
          "url": "https://link.coupang.com/a/ftuPB2shYy",
          "_ts": 1784337095.9023628
        },
        {
          "name": "비플레인 녹두 모공 클리어링 라하 토너 265ml 2개",
          "price": "9,400원",
          "discount_rate": 59,
          "priceAt": "07.18 09:23",
          "image": "//thumbnail.coupangcdn.com/thumbnails/remote/492x492ex/image/retail/images/432178966017652-8d2fcdf2-be89-4b33-8a70-6bb493b750a9.jpg",
          "url": "https://link.coupang.com/a/ftrmywK73c",
          "_ts": 1784334184.769176
        },
        {
          "name": "닥터세닥 슈퍼와이드 칫솔 10개입",
          "price": "5,960원",
          "discount_rate": 45,
          "priceAt": "07.18 09:10",
          "image": "//thumbnail.coupangcdn.com/thumbnails/remote/492x492ex/image/retail/images/2025/05/21/17/4/d727a0a8-176e-45e0-9520-aeb19fb7ab48.jpg",
          "url": "https://link.coupang.com/a/ftqtUH3bWe",
          "_ts": 1784333443.033314
        },
        {
          "name": "크리넥스 알러지 케어 로션 천연펄프 각티슈 3겹, 150매입, 3개",
          "price": "9,400원",
          "discount_rate": 35,
          "priceAt": "07.18 09:10",
          "image": "//thumbnail.coupangcdn.com/thumbnails/remote/492x492ex/image/retail/images/225511600992669-1ddaff19-9da3-4956-a51f-bb9daf0e0bcc.jpg",
          "url": "https://link.coupang.com/a/ftqs2IRh7s",
          "_ts": 1784333433.3158772
        },
        {
          "name": "비비고 얇은피 큰 채소가득 고기만두 고기 & 양배추 (냉동), 1kg, 1개",
          "price": "9,980원",
          "discount_rate": 24,
          "priceAt": "07.18 07:45",
          "image": "//thumbnail.coupangcdn.com/thumbnails/remote/492x492ex/image/rs_quotation_api/xw2ew7hw/73b08a8fc09740dda9f64d997b878f2d.jpg",
          "url": "https://link.coupang.com/a/ftkpSjjTB6",
          "_ts": 1784328353.872931
        },
        {
          "name": "롯데웰푸드 칙촉, 168g, 4개",
          "price": "8,410원",
          "discount_rate": 16,
          "priceAt": "07.18 07:35",
          "image": "//thumbnail.coupangcdn.com/thumbnails/remote/492x492ex/image/1025_amir_coupang_oct_80k/0cdd/ee3fbe90a34f86cc9a124702e58bdda1d899ebb05468bc75b975d2ced720.jpg",
          "url": "https://link.coupang.com/a/ftjGD7i6Kq",
          "_ts": 1784327738.974369
        },
        {
          "name": "글래드 매직랩 미니 20cm*40m*40m*1개",
          "price": "9,030원",
          "discount_rate": 25,
          "priceAt": "07.18 07:33",
          "image": "//thumbnail.coupangcdn.com/thumbnails/remote/492x492ex/image/retail/images/2026/05/26/15/6/8e3ddb0e-375a-4a5d-88da-66e2a5a3710d.jpg",
          "url": "https://link.coupang.com/a/ftjwO3eKDA",
          "_ts": 1784327608.036003
        },
        {
          "name": "르샤트라1802 건조기 시트 섬유유연제 클린코튼향 본품 140매*1개",
          "price": "8,770원",
          "discount_rate": 27,
          "priceAt": "07.18 07:29",
          "image": "//thumbnail.coupangcdn.com/thumbnails/remote/492x492ex/image/vendor_inventory/dca6/e8339989dd84f3e80594fcadc26b64c97d4c9b2564666960357ef943d30c.jpg",
          "url": "https://link.coupang.com/a/ftjea1VFi8",
          "_ts": 1784327354.323235
        },
        {
          "name": "자연은 더말린 제로 복숭아 음료, 500ml, 20개",
          "price": "12,240원",
          "discount_rate": 18,
          "priceAt": "07.18 07:10",
          "image": "//thumbnail.coupangcdn.com/thumbnails/remote/492x492ex/image/retail/images/2577478947818461-4abf07a1-843f-4043-a0b7-fc65b47bca5c.jpg",
          "url": "https://link.coupang.com/a/fthTXB9hNk",
          "_ts": 1784326240.022285
        },
        {
          "name": "비피아이스포츠 아이소 HD 퓨어 아이솔레이트 프로틴 초콜릿 브라우니 2.208kg*1개",
          "price": "70,430원",
          "discount_rate": 17,
          "priceAt": "07.18 07:04",
          "image": "//thumbnail.coupangcdn.com/thumbnails/remote/492x492ex/image/vendor_inventory/8c75/88f32b3dfb87fb4ecea31ed432c1a14524761d4083f46061ba48a791f571.jpg",
          "url": "https://link.coupang.com/a/fthrdd0nue",
          "_ts": 1784325850.282201
        }
      ]
    }
  ]
}
